serialengine/__init__.py
serialengine/constants.py
serialengine/hub.py
serialengine/transport.py
tests/__init__.py
tests/transport.test.py
mq.engine-0.0.1.dist-info/LICENSE
mq.engine-0.0.1.dist-info/METADATA
mq.engine-0.0.1.dist-info/WHEEL
mq.engine-0.0.1.dist-info/top_level.txt
mq.engine-0.0.1.dist-info/RECORD
